{
  "source": "C:\\Users\\Luke_C\\Desktop\\JiraObservationMonitor\\data\\user_access_source_real.csv",
  "schema": "jom-user-access-source-v1",
  "summary": {
    "users_analyzed": 3,
    "total_site_assignments": 6,
    "average_sites_per_user": 2.0,
    "high_duplication_users": 1,
    "medium_duplication_users": 1,
    "low_duplication_users": 1
  },
  "users": [
    {
      "id": "test.three@gaminglabs.com",
      "name": "Test Person Three",
      "email": "test.three@gaminglabs.com",
      "status": "active",
      "site_count": 3,
      "sites": [
        "GLI Delivery TM",
        "GLI Global Technology",
        "GLI IT Project"
      ],
      "category": "high"
    },
    {
      "id": "test.one@gaminglabs.com",
      "name": "Test Person One",
      "email": "test.one@gaminglabs.com",
      "status": "active",
      "site_count": 2,
      "sites": [
        "GLI Global Technology",
        "GLI IT Project"
      ],
      "category": "medium"
    },
    {
      "id": "test.two@gaminglabs.com",
      "name": "Test Person Two",
      "email": "test.two@gaminglabs.com",
      "status": "active",
      "site_count": 1,
      "sites": [
        "GLI Delivery TM"
      ],
      "category": "low"
    }
  ],
  "notes": [
    "Imported from user access CSV source.",
    "Headers and cell values are trimmed before processing.",
    "True access values: User, Yes, True, 1, Active, Enabled, Licensed, Y."
  ]
}